readme_utils/__init__.py
readme_utils/__version__.py
readme_utils/core.py
readme_utils/data/bibliography.bib
readme_utils/data/format.yaml
readme_utils/data/header.tex
readme_utils/data/readme.md
readme_utils/data/readme_settings.json
readme_utils-0.1.3.dist-info/METADATA
readme_utils-0.1.3.dist-info/RECORD
readme_utils-0.1.3.dist-info/WHEEL
readme_utils-0.1.3.dist-info/entry_points.txt
readme_utils-0.1.3.dist-info/top_level.txt
