Metadata-Version: 2.1
Name: readme-utils
Version: 0.1.3
Summary: A small utility for creating beautiful pandoc markdown readme files.
Home-page: https://github.com/tormenteddan/readme_utils
Author: Daniel Aragon
Author-email: daniel.aragon@ciencias.unam.mx
License: MIT
Platform: UNKNOWN
Classifier: License :: OSI Approved :: MIT License
Classifier: Programming Language :: Python
Classifier: Programming Language :: Python :: 3
Classifier: Programming Language :: Python :: 3.7
Classifier: Programming Language :: Python :: Implementation :: CPython
Classifier: Programming Language :: Python :: Implementation :: PyPy
Requires-Python: >=3.7.0
Requires-Dist: Click
